jupyterlab_notebook_awareness/__init__.py
jupyterlab_notebook_awareness/_version.py
jupyterlab_notebook_awareness-0.1.0.data/data/share/jupyter/labextensions/jupyterlab-notebook-awareness/build_log.json
jupyterlab_notebook_awareness-0.1.0.data/data/share/jupyter/labextensions/jupyterlab-notebook-awareness/package.json
jupyterlab_notebook_awareness-0.1.0.data/data/share/jupyter/labextensions/jupyterlab-notebook-awareness/static/lib_index_js.c90be29b394dfaea4373.js
jupyterlab_notebook_awareness-0.1.0.data/data/share/jupyter/labextensions/jupyterlab-notebook-awareness/static/lib_index_js.c90be29b394dfaea4373.js.map
jupyterlab_notebook_awareness-0.1.0.data/data/share/jupyter/labextensions/jupyterlab-notebook-awareness/static/remoteEntry.f1d073b698c24a7022a9.js
jupyterlab_notebook_awareness-0.1.0.data/data/share/jupyter/labextensions/jupyterlab-notebook-awareness/static/remoteEntry.f1d073b698c24a7022a9.js.map
jupyterlab_notebook_awareness-0.1.0.data/data/share/jupyter/labextensions/jupyterlab-notebook-awareness/static/style.js
jupyterlab_notebook_awareness-0.1.0.data/data/share/jupyter/labextensions/jupyterlab-notebook-awareness/static/style_index_js.bf545ecf9813d8864683.js
jupyterlab_notebook_awareness-0.1.0.data/data/share/jupyter/labextensions/jupyterlab-notebook-awareness/static/style_index_js.bf545ecf9813d8864683.js.map
jupyterlab_notebook_awareness-0.1.0.data/data/share/jupyter/labextensions/jupyterlab-notebook-awareness/install.json
jupyterlab_notebook_awareness-0.1.0.dist-info/METADATA
jupyterlab_notebook_awareness-0.1.0.dist-info/WHEEL
jupyterlab_notebook_awareness-0.1.0.dist-info/licenses/LICENSE
jupyterlab_notebook_awareness-0.1.0.dist-info/RECORD
