Metadata-Version: 2.4
Name: jupyterlab_notebook_awareness
Version: 0.1.0
Summary: A JupyterLab extension that tracks a user's current notebook and cell.
Project-URL: Homepage, https://github.com/jupyter-ai-contrib/jupyterlab-notebook-awareness
Project-URL: Bug Tracker, https://github.com/jupyter-ai-contrib/jupyterlab-notebook-awareness/issues
Project-URL: Repository, https://github.com/jupyter-ai-contrib/jupyterlab-notebook-awareness.git
Author-email: Zach Sailer <zachsailer@gmail.com>
License: BSD 3-Clause License
License-File: LICENSE
Keywords: jupyter,jupyterlab,jupyterlab-extension
Classifier: Framework :: Jupyter
Classifier: Framework :: Jupyter :: JupyterLab
Classifier: Framework :: Jupyter :: JupyterLab :: 4
Classifier: Framework :: Jupyter :: JupyterLab :: Extensions
Classifier: Framework :: Jupyter :: JupyterLab :: Extensions :: Prebuilt
Classifier: License :: OSI Approved :: BSD License
Classifier: Programming Language :: Python
Classifier: Programming Language :: Python :: 3
Classifier: Programming Language :: Python :: 3.9
Classifier: Programming Language :: Python :: 3.10
Classifier: Programming Language :: Python :: 3.11
Classifier: Programming Language :: Python :: 3.12
Classifier: Programming Language :: Python :: 3.13
Requires-Python: >=3.9
